CHANGES
LICENSE
README
setup.py
tests.py
SQLAlchemy_Enum_Dict.egg-info/PKG-INFO
SQLAlchemy_Enum_Dict.egg-info/SOURCES.txt
SQLAlchemy_Enum_Dict.egg-info/dependency_links.txt
SQLAlchemy_Enum_Dict.egg-info/not-zip-safe
SQLAlchemy_Enum_Dict.egg-info/requires.txt
SQLAlchemy_Enum_Dict.egg-info/top_level.txt
sqlalchemy_enum_dict/__init__.py
sqlalchemy_enum_dict/columns.py
sqlalchemy_enum_dict/extensions.py