Metadata-Version: 1.1
Name: SQLAlchemy-Enum-Dict
Version: 0.1.2
Summary: Adds convinient EnumDict column to sqlalchemy
Home-page: http://bitbucket.org/ponomar/sqlalchemy-enum-dict
Author: Vitalii Ponomar
Author-email: vitalii.ponomar@gmail.com
License: BSD
Keywords: sqlalchemy enum
Platform: any
Classifier: Development Status :: 4 - Beta
Classifier: Intended Audience :: Developers
Classifier: License :: OSI Approved :: BSD License
Classifier: Operating System :: OS Independent
Classifier: Programming Language :: Python
